[
    {
        "userId": 1,
        "id": "1",
        "name": "Thapa Techical",
        "email": "thapa@technical.com",
        "website": "https://www.youtube.com/thapatechnical",
        "mobile": "1234567899",
        "image": "https://instagram.flhe24-1.fna.fbcdn.net/v/t51.2885-15/272080376_372185344575138_2770405670399132073_n.webp?stp=dst-jpg_e35_s150x150&_nc_ht=instagram.flhe24-1.fna.fbcdn.net&_nc_cat=106&_nc_ohc=Mdioj54jeLoAX_f8eRV&edm=AOQ1c0wBAAAA&ccb=7-5&oh=00_AT-peL2r0EKEo6yJ9Toap_DPD0gzQ21RCa9jNfLXVfPGvQ&oe=62F5E9DF&_nc_sid=8fd12b 150w,https://instagram.flhe24-1.fna.fbcdn.net/v/t51.2885-15/272080376_372185344575138_2770405670399132073_n.webp?stp=dst-jpg_e35_s240x240&_nc_ht=instagram.flhe24-1.fna.fbcdn.net&_nc_cat=106&_nc_ohc=Mdioj54jeLoAX_f8eRV&edm=AOQ1c0wBAAAA&ccb=7-5&oh=00_AT-LDwpmu7bFYslhVW7VJ3jBWsI-5TiX5a35t_oeEvwy-Q&oe=62F5E9DF&_nc_sid=8fd12b 240w,https://instagram.flhe24-1.fna.fbcdn.net/v/t51.2885-15/272080376_372185344575138_2770405670399132073_n.webp?stp=dst-jpg_e35_s320x320&_nc_ht=instagram.flhe24-1.fna.fbcdn.net&_nc_cat=106&_nc_ohc=Mdioj54jeLoAX_f8eRV&edm=AOQ1c0wBAAAA&ccb=7-5&oh=00_AT-hVydK9RwcLAX604FfWzn-8mjcWFZt5RkTjrnkMhVeag&oe=62F5E9DF&_nc_sid=8fd12b 320w,https://instagram.flhe24-1.fna.fbcdn.net/v/t51.2885-15/272080376_372185344575138_2770405670399132073_n.webp?stp=dst-jpg_e35_s480x480&_nc_ht=instagram.flhe24-1.fna.fbcdn.net&_nc_cat=106&_nc_ohc=Mdioj54jeLoAX_f8eRV&edm=AOQ1c0wBAAAA&ccb=7-5&oh=00_AT8nAvua5oKo9uvt4Inm4larQ_rXccA5gaCVpOebsX8p4g&oe=62F5E9DF&_nc_sid=8fd12b 480w,https://instagram.flhe24-1.fna.fbcdn.net/v/t51.2885-15/272080376_372185344575138_2770405670399132073_n.webp?stp=dst-jpg_e35_s640x640_sh0.08&_nc_ht=instagram.flhe24-1.fna.fbcdn.net&_nc_cat=106&_nc_ohc=Mdioj54jeLoAX_f8eRV&edm=AOQ1c0wBAAAA&ccb=7-5&oh=00_AT9DFpHEVjUIVWlubN3lJw5aSDyfQ4EIkJ2Ck1tJBmHNSQ&oe=62F5E9DF&_nc_sid=8fd12b 640w",
        "description": "quia et suscipit\nsuscipit recusandae consequuntur expedita et cum\nreprehenderit molestiae ut ut quas totam\nnostrum rerum est autem sunt rem eveniet architecto"
    },
    {
        "userId": 2,
        "id": "2",
        "name": "vinod thapa",
        "email": "vinod@technical.com",
        "website": "https://www.youtube.com/thapatechnical",
        "mobile": "1234567899",
        "image": "https://images.pexels.com/photos/547593/pexels-photo-547593.jpeg?auto=compress&cs=tinysrgb&dpr=2&h=750&w=1260",
        "description": "est rerum tempore vitae\nsequi sint nihil reprehenderit dolor beatae ea dolores neque\nfugiat blanditiis voluptate porro vel nihil molestiae ut reiciendis\nqui aperiam non debitis possimus qui neque nisi nulla"
    },
    {
        "userId": 3,
        "id": "3",
        "name": "Young Bahadur",
        "email": "Bahadur@young.com",
        "website": "https://www.youtube.com/thapatechnical",
        "mobile": "1234567899",
        "image": "https://images.pexels.com/photos/1526814/pexels-photo-1526814.jpeg?auto=compress&cs=tinysrgb&dpr=2&h=750&w=1260",
        "description": "et iusto sed quo iure\nvoluptatem occaecati omnis eligendi aut ad\nvoluptatem doloribus vel accusantium quis pariatur\nmolestiae porro eius odio et labore et velit aut"
    },
    {
        "userId": 4,
        "id": "4",
        "name": "vinod Techical",
        "email": "vinod@technical.com",
        "website": "https://www.youtube.com/thapatechnical",
        "mobile": "1234567899",
        "image": "https://images.pexels.com/photos/220453/pexels-photo-220453.jpeg?auto=compress&cs=tinysrgb&dpr=2&h=750&w=1260",
        "description": "ullam et saepe reiciendis voluptatem adipisci\nsit amet autem assumenda provident rerum culpa\nquis hic commodi nesciunt rem tenetur doloremque ipsam iure\nquis sunt voluptatem rerum illo velit"
    },
    {
        "userId": 5,
        "id": "5",
        "name": "Susbscribe Techical",
        "email": "Susbscribe@technical.com",
        "website": "https://www.youtube.com/thapatechnical",
        "mobile": "1234567899",
        "image": "https://images.pexels.com/photos/2905828/pexels-photo-2905828.jpeg?auto=compress&cs=tinysrgb&dpr=1&w=500",
        "description": "repudiandae veniam quaerat sunt sed\nalias aut fugiat sit autem sed est\nvoluptatem omnis possimus esse voluptatibus quis\nest aut tenetur dolor neque"
    },
    {
        "userId": 6,
        "id": "6",
        "name": "Test Techical",
        "email": "Test@technical.com",
        "website": "https://www.youtube.com/thapatechnical",
        "mobile": "1234567899",
        "image": "https://images.pexels.com/photos/220453/pexels-photo-220453.jpeg?auto=compress&cs=tinysrgb&dpr=2&h=750&w=1260",
        "description": "ut aspernatur corporis harum nihil quis provident sequi\nmollitia nobis aliquid molestiae\nperspiciatis et ea nemo ab reprehenderit accusantium quas\nvoluptate dolores velit et doloremque molestiae"
    },
    {
        "userId": 7,
        "id": "7",
        "name": "Like Techical",
        "email": "Like@technical.com",
        "website": "https://www.youtube.com/thapatechnical",
        "mobile": "1234567899",
        "image": "https://images.pexels.com/photos/220453/pexels-photo-220453.jpeg?auto=compress&cs=tinysrgb&dpr=2&h=750&w=1260",
        "description": "dolore placeat quibusdam ea quo vitae\nmagni quis enim qui quis quo nemo aut saepe\nquidem repellat excepturi ut quia\nsunt ut sequi eos ea sed quas"
    },
    {
        "userId": 8,
        "id": "8",
        "name": "Comment Techical",
        "email": "Comment@technical.com",
        "website": "https://www.youtube.com/thapatechnical",
        "mobile": "1234567899",
        "image": "https://images.pexels.com/photos/220453/pexels-photo-220453.jpeg?auto=compress&cs=tinysrgb&dpr=2&h=750&w=1260",
        "description": "dignissimos aperiam dolorem qui eum\nfacilis quibusdam animi sint suscipit qui sint possimus cum\nquaerat magni maiores excepturi\nipsam ut commodi dolor voluptatum modi aut vitae"
    },
    {
        "userId": 9,
        "id": "9",
        "name": "Share Techical",
        "email": "Share@technical.com",
        "website": "https://www.youtube.com/thapatechnical",
        "mobile": "1234567899",
        "image": "https://images.pexels.com/photos/220453/pexels-photo-220453.jpeg?auto=compress&cs=tinysrgb&dpr=2&h=750&w=1260",
        "description": "consectetur animi nesciunt iure dolore\nenim quia ad\nveniam autem ut quam aut nobis\net est aut quod aut provident voluptas autem voluptas"
    }
]  

